<?xml version="1.0" encoding="UTF-8"?>
<monster name="Burning Demon" nameDescription="a burning demon" race="fire" experience="6000" speed="275" manacost="10000">
  <health now="50000" max="50000"/>
  <look type="35" corpse="5995"/>
  <targetchange interval="5000" chance="8"/>
  <strategy attack="90" defense="10"/>
  <flags>
    <flag summonable="0"/>
    <flag attackable="1"/>
    <flag hostile="1"/>
    <flag illusionable="0"/>
    <flag convinceable="0"/>
    <flag pushable="0"/>
    <flag canpushitems="1"/>
    <flag canpushcreatures="1"/>
    <flag targetdistance="1"/>
    <flag staticattack="90"/>
    <flag runonhealth="0"/>
  </flags>
  <attacks>
    <attack name="melee" interval="2000" skill="200" attack="80"/>
    <attack name="manadrain" interval="2000" chance="22" range="7" min="0" max="-1200"/>
    <attack name="fire" interval="2000" chance="34" range="7" radius="7" target="1" min="-1500" max="-2500">
		<attribute key="shootEffect" value="fire"/>
		<attribute key="areaEffect" value="firearea"/>
	</attack>
    <attack name="firefield" interval="2000" chance="12" range="7" radius="1" target="1">
		<attribute key="shootEffect" value="fire"/>
	</attack>
    <attack name="lifedrain" interval="2000" chance="25" length="8" spread="0" min="-300" max="-467">
		<attribute key="areaEffect" value="purpleenergy"/>
	</attack>
	<attack name="speed" interval="2000" chance="15" target="1" speedchange="-750" duration="30000">
		<attribute key="shootEffect" value="suddendeath"/>
	</attack>
	<attack name="energy" interval="3000" chance="18" range="1" target="1" min="-210" max="-300">
		<attribute key="areaEffect" value="purpleenergy"/>
	</attack>
  </attacks>
  <defenses armor="55" defense="55">
    <defense name="healing" interval="2000" chance="100" min="3030" max="2400">
      <attribute key="areaEffect" value="blueshimmer"/>
    </defense>
	<defense name="speed" interval="1000" chance="8" speedchange="290" duration="5000">
      <attribute key="areaEffect" value="redshimmer"/>
    </defense>
  </defenses>
	<elements>
		<element physicalPercent="30"/>
		<element energyPercent="50"/>
		<element earthPercent="40"/>
		<element icePercent="-12"/>
		<element holyPercent="-12"/>
		<element deathPercent="30"/>
	</elements>
  <immunities>
    <immunity fire="1"/>
    <immunity drown="1"/>
    <immunity paralyze="1"/>
    <immunity invisible="1"/>
  </immunities>
  <summons maxSummons="1">
    <summon name="fire elemental" interval="1000" chance="12"/>
  </summons>
  <voices interval="5000" chance="10">
    <voice sentence="THE PORTAL WAS OPEN!" yell="1"/>
  </voices>
  <loot>
</loot>
</monster>
