<?xml version="1.0"?>
<npc name="Nah'Bob" floorchange="0" walkinterval="2000" speed="220">
	<health now="150" max="150"/>
	<look type="80" head="95" body="132" legs="0" feet="0" addons="0"/>
  
  <interaction range="3" idletime="0" defaultpublic="0">

	<include file="events_shop.xml"/>
    <include file="djinns.xml"/>
    
    <interact keywords="hi" focus="1">
      <keywords>hello</keywords>
      
      <response text="Hello. How may I help you |NAME|?"/>
    </interact>

    <interact keywords="bye" focus="0">
      <keywords>farewell</keywords>

      <response text="It was a pleasure to help you."/>
    </interact>

    <interact event="onPlayerLeave" focus="0">
      <response text="It was a pleasure to help you |NAME|."/>
    </interact>
    
    <interact keywords="name">
      <response text="My name is |NPCNAME|."/>
    </interact>

    <interact keywords="job">
      <response text="I am a merchant, my job is to serve you!"/>
    </interact>

    <interact keywords="wares">
		<response text="I sell and buy some itens!, ask {trade} and I will see my offers."/>
    </interact>
	
	<interact keywords="trade">
		<list>djinn_nah</list>

		<response>
			<action name="script">
			<![CDATA[
			  openShopWindow(cid, itemlist, -1, -1)
			]]>
			</action>
		</response>
	</interact>
	

  </interaction>
  
</npc>